Metadata-Version: 2.1
Name: whistleblower
Version: 0.0.1
Summary: This project is used to alarm emergency information to your mobile phone on webhook service
Home-page: UNKNOWN
Author: Y.S. Wang
Author-email: yasen@yasenstudio.com
License: MIT Licence
Platform: UNKNOWN
